dgii_rnc/__init__.py
dgii_rnc/dgii_rnc.py
dgii_rnc-0.6.dist-info/METADATA
dgii_rnc-0.6.dist-info/WHEEL
dgii_rnc-0.6.dist-info/top_level.txt
dgii_rnc-0.6.dist-info/RECORD
