Metadata-Version: 2.1
Name: dgii_rnc
Version: 0.6
Home-page: https://github.com/lcgarc1a/dgii_rnc
Author: Luis C Garcia
License: MIT License
Project-URL: Repository, https://github.com/lcgarc1a/dgii_rnc.git
Project-URL: Issues, https://github.com/lcgarc1a/dgii_rnc/issues
Keywords: dgii,rnc
Classifier: Development Status :: 5 - Production/Stable
Classifier: Intended Audience :: Information Technology
Classifier: Topic :: Utilities
Classifier: License :: OSI Approved :: MIT License
Classifier: Programming Language :: Python :: 3.11
Requires-Python: >=3.11
Requires-Dist: polars
Requires-Dist: selenium
Requires-Dist: webdriver-manager
